BaraaValidator/__init__.py
BaraaValidator/transactionValidators.py
BaraaValidator/gRPC/__init__.py
BaraaValidator/gRPC/__transactionValidator_pb2.py
BaraaValidator/gRPC/__transactionValidator_pb2_grpc.py
BaraaValidator/gRPC/validator_client.py
BaraaValidator/gRPC/validator_server.py
Baraa_Validator-0.1.1.dist-info/DESCRIPTION.rst
Baraa_Validator-0.1.1.dist-info/METADATA
Baraa_Validator-0.1.1.dist-info/RECORD
Baraa_Validator-0.1.1.dist-info/WHEEL
Baraa_Validator-0.1.1.dist-info/metadata.json
Baraa_Validator-0.1.1.dist-info/top_level.txt
