Metadata-Version: 2.0
Name: Baraa-Validator
Version: 0.1.1
Summary: A simple library that provide multiple useful validation methods.
Home-page: UNKNOWN
Author: Baraa Abu-Alrub
Author-email: UNKNOWN
License: MIT
Platform: UNKNOWN
